[
  {
    "id": "mok",
    "name": "MOK Specialty Coffee",
    "image": "https://images.unsplash.com/photo-1453614512568-c4024d13c247?w=800&q=80&auto=format&fit=crop",
    "quartier": "Dansaert",
    "address": "Rue Antoine Dansaert 196, 1000 Bruxelles",
    "lat": 50.8531,
    "lng": 4.3417,
    "tags": ["specialty", "travailler"],
    "rating": 4.5,
    "signature": "Filtre V60 single origin, torréfié maison",
    "wifi": true,
    "plugs": true,
    "price": "€€",
    "hours": "Lun–Ven 8h–17h · Sam–Dim 9h–17h",
    "blurb": "Le torréfacteur de référence côté Dansaert. Grandes tables, lumière naturelle, et un filtre qui change selon les arrivages — parfait pour poser le laptop un matin entier."
  },
  {
    "id": "cafe-capitale",
    "name": "Café Capitale",
    "image": "https://images.unsplash.com/photo-1600093463592-8e36ae95ef56?w=800&q=80&auto=format&fit=crop",
    "quartier": "Centre",
    "address": "Rue du Midi 45, 1000 Bruxelles",
    "lat": 50.8446,
    "lng": 4.3494,
    "tags": ["specialty", "travailler"],
    "rating": 4,
    "signature": "Espresso blend maison, ambiance vinyle",
    "wifi": true,
    "plugs": true,
    "price": "€€",
    "hours": "Lun–Ven 7h30–18h · Sam–Dim 9h–18h",
    "blurb": "Une institution du centre. Le genre d'endroit où le barista te reconnaît à la troisième visite et lance ton espresso avant que tu commandes."
  },
  {
    "id": "buddy-buddy",
    "name": "Buddy Buddy",
    "image": "https://images.unsplash.com/photo-1509042239860-f550ce710b93?w=800&q=80&auto=format&fit=crop",
    "quartier": "Châtelain",
    "address": "Rue du Bailli, 1050 Ixelles",
    "lat": 50.8266,
    "lng": 4.3620,
    "tags": ["instagrammable", "date"],
    "rating": 4,
    "signature": "Latte au beurre de noisette maison",
    "wifi": false,
    "plugs": false,
    "price": "€€",
    "hours": "Lun–Dim 8h–18h",
    "blurb": "Décor pastel, laits végétaux maison et une signature nut-butter latte qui divise autant qu'elle fidélise. Le spot photogénique par excellence."
  },
  {
    "id": "parlor",
    "name": "Parlor Coffee",
    "image": "https://images.unsplash.com/photo-1525193612562-0ec53b0e5d7c?w=800&q=80&auto=format&fit=crop",
    "quartier": "Saint-Gilles",
    "address": "Chaussée de Charleroi 203, 1060 Saint-Gilles",
    "lat": 50.8225,
    "lng": 4.3573,
    "tags": ["travailler", "brunch"],
    "rating": 4.5,
    "signature": "Banana bread + batch brew",
    "wifi": true,
    "plugs": true,
    "price": "€€",
    "hours": "Lun–Ven 8h–18h · Sam–Dim 9h–18h",
    "blurb": "Grande salle, briques apparentes, playlist calme. Le QG officieux des freelances de Saint-Gilles — arrive avant 10h pour la table près de la fenêtre."
  },
  {
    "id": "or-coffee",
    "name": "OR Coffee Bar",
    "image": "https://images.unsplash.com/photo-1545418314-7ce0b9b53901?w=800&q=80&auto=format&fit=crop",
    "quartier": "Bourse",
    "address": "Rue Auguste Orts 9, 1000 Bruxelles",
    "lat": 50.8480,
    "lng": 4.3480,
    "tags": ["specialty", "travailler"],
    "rating": 4,
    "signature": "Espresso d'Éthiopie, torréfaction claire",
    "wifi": true,
    "plugs": true,
    "price": "€€",
    "hours": "Lun–Dim 8h–18h",
    "blurb": "Torréfacteur belge historique à deux pas de la Bourse. Deux étages : le haut pour bosser au calme, le bas pour regarder passer Bruxelles."
  },
  {
    "id": "my-little-cup",
    "name": "My Little Cup",
    "image": "https://images.unsplash.com/photo-1495474472287-4d71bcdd2085?w=800&q=80&auto=format&fit=crop",
    "quartier": "Sainte-Catherine",
    "address": "Quartier Sainte-Catherine, 1000 Bruxelles",
    "lat": 50.8508,
    "lng": 4.3465,
    "tags": ["specialty"],
    "rating": 4,
    "signature": "Flat white serré, à emporter vers le canal",
    "wifi": false,
    "plugs": false,
    "price": "€",
    "hours": "Lun–Sam 8h–16h",
    "blurb": "Minuscule comptoir, immense précision. Pas vraiment un spot pour s'installer : on prend son café, on marche jusqu'au quai, et c'est très bien comme ça."
  },
  {
    "id": "kaffabar",
    "name": "Kaffabar",
    "image": "https://images.unsplash.com/photo-1445116572660-236099ec97a0?w=800&q=80&auto=format&fit=crop",
    "quartier": "Flagey",
    "address": "Quartier Flagey, 1050 Ixelles",
    "lat": 50.8280,
    "lng": 4.3705,
    "tags": ["date", "specialty"],
    "rating": 4,
    "signature": "Cappuccino + cannelle, à deux pas des étangs",
    "wifi": true,
    "plugs": false,
    "price": "€€",
    "hours": "Lun–Dim 8h30–18h",
    "blurb": "Petit, chaleureux, un peu bruyant le week-end — exactement ce qu'il faut pour un premier rendez-vous sans pression, avant une balade aux étangs d'Ixelles."
  },
  {
    "id": "fika",
    "name": "Fika",
    "image": "https://images.unsplash.com/photo-1534040385115-33dcb3acba5b?w=800&q=80&auto=format&fit=crop",
    "quartier": "Saint-Boniface",
    "address": "Quartier Saint-Boniface, 1050 Ixelles",
    "lat": 50.8330,
    "lng": 4.3670,
    "tags": ["brunch", "date", "instagrammable"],
    "rating": 4,
    "signature": "Kanelbullar + filtre, comme à Stockholm",
    "wifi": true,
    "plugs": false,
    "price": "€€",
    "hours": "Mer–Dim 9h–17h",
    "blurb": "Le fika suédois transplanté à Saint-Boniface : brioches à la cardamome, céramique artisanale et un rythme volontairement lent. Réserve le week-end."
  },
  {
    "id": "belga-co",
    "name": "Belga & Co",
    "image": "https://images.unsplash.com/photo-1511920170033-f8396924c348?w=800&q=80&auto=format&fit=crop",
    "quartier": "Bailli",
    "address": "Rue du Bailli, 1050 Ixelles",
    "lat": 50.8245,
    "lng": 4.3598,
    "tags": ["specialty", "brunch"],
    "rating": 4,
    "signature": "Torréfaction maison + pancakes du week-end",
    "wifi": true,
    "plugs": true,
    "price": "€€",
    "hours": "Lun–Dim 8h–18h",
    "blurb": "Torréfacteur de quartier au sens propre : les sacs de grains s'empilent derrière le comptoir. Le brunch du samedi vaut le déplacement à lui seul."
  },
  {
    "id": "jat-cafe",
    "name": "Jat' Café",
    "image": "https://images.unsplash.com/photo-1493857671505-72967e2e2760?w=800&q=80&auto=format&fit=crop",
    "quartier": "Saint-Gilles",
    "address": "Parvis de Saint-Gilles, 1060 Saint-Gilles",
    "lat": 50.8285,
    "lng": 4.3455,
    "tags": ["date", "instagrammable"],
    "rating": 4,
    "signature": "Chaï latte maison, canapés dépareillés",
    "wifi": true,
    "plugs": false,
    "price": "€",
    "hours": "Mar–Dim 9h–18h",
    "blurb": "L'âme du Parvis en version café : mobilier chiné, habitués qui refont le monde, lumière dorée en fin d'après-midi. On y vient pour une heure, on y reste trois."
  },
  {
    "id": "cafe-velvet",
    "name": "Café Velvet",
    "image": "https://images.unsplash.com/photo-1511081692775-05d0f180a065?w=800&q=80&auto=format&fit=crop",
    "quartier": "Louise",
    "address": "Quartier Louise, 1050 Bruxelles",
    "lat": 50.8330,
    "lng": 4.3560,
    "tags": ["travailler", "instagrammable"],
    "rating": 3.5,
    "signature": "Oat latte + carrot cake",
    "wifi": true,
    "plugs": true,
    "price": "€€€",
    "hours": "Lun–Dim 8h–19h",
    "blurb": "Grand, lumineux, design soigné — le café-bureau assumé du quartier Louise. Plus cher que la moyenne, mais les prises à chaque table font vite oublier l'addition."
  },
  {
    "id": "chouke",
    "name": "Chouke",
    "image": "https://images.unsplash.com/photo-1525610553991-2bede1a236e2?w=800&q=80&auto=format&fit=crop",
    "quartier": "Marolles",
    "address": "Quartier des Marolles, 1000 Bruxelles",
    "lat": 50.8390,
    "lng": 4.3470,
    "tags": ["brunch", "date"],
    "rating": 4.5,
    "signature": "Pain perdu brioché + filtre doux",
    "wifi": false,
    "plugs": false,
    "price": "€€",
    "hours": "Jeu–Lun 9h–16h",
    "blurb": "Un surnom bruxellois en guise d'enseigne, des assiettes généreuses et zéro chichi. Le dimanche matin idéal : brocante du jeu de balle, puis pain perdu chez Chouke."
  }
]